nginxcsp/__init__.py
nginxcsp/__main__.py
nginxcsp/app/__init__.py
nginxcsp/app/application.py
nginxcsp/app/generator.py
nginxcsp/app/test_generator.py
nginxcsp/cli/__init__.py
nginxcsp/cli/cli.py
nginxcsp/html_parser/__init__.py
nginxcsp/html_parser/ref_parser.py
nginxcsp/html_parser/test_ref_parser.py
nginxcsp/nginx_parser/__init__.py
nginxcsp/nginx_parser/exceptions.py
nginxcsp/nginx_parser/nginx_dumper.py
nginxcsp/nginx_parser/nginx_parser.py
nginxcsp/nginx_parser/test_nginx_dumper.py
nginxcsp/nginx_parser/test_nginx_parser.py
nginxcsp/nginx_parser/test_token.py
nginxcsp/nginx_parser/test_token_types.py
nginxcsp/nginx_parser/test_tokenizer.py
nginxcsp/nginx_parser/token.py
nginxcsp/nginx_parser/token_types.py
nginxcsp/nginx_parser/tokenizer.py
nginxcsp-0.1.0.dist-info/LICENSE
nginxcsp-0.1.0.dist-info/METADATA
nginxcsp-0.1.0.dist-info/WHEEL
nginxcsp-0.1.0.dist-info/entry_points.txt
nginxcsp-0.1.0.dist-info/top_level.txt
nginxcsp-0.1.0.dist-info/RECORD
