Metadata-Version: 2.1
Name: nginxcsp
Version: 0.1.0
Summary: Generate NGINX Content-Security-Policy headers from HTML     files
Home-page: https://github.com/GianOrtiz/nginxcsp
Author: Gian Ortiz
Author-email: brksgian@gmail.com
License: UNKNOWN
Project-URL: Source Code, https://github.com/GianOrtiz/nginxcsp
Keywords: nginx config security
Platform: UNKNOWN
Classifier: Programming Language :: Python :: 3
Classifier: License :: OSI Approved :: MIT License
Classifier: Operating System :: OS Independent
